{".FVER":1,".FILE_VERSION":1,"Archive ID":"701599",".CREATOR":"4ilda7s9tsccna6t",".MIME":"image/png",".IMAGE_HEIGHT":"4004",".NAME":"MOM_EST_701599_IE00165_V00_0001.png",".FILE_NAME":"MOM_EST_701599_IE00165_V00_0001.png","Handle of the 3D":"IE00165",".IMAGE_WIDTH":"1435",".FILE_ENCODING":"ds1_1","Squeeze Identifier":"UMR 5189 HiSoMA",".FILE_MODIFIED":1545080912000,".FILE_UPLOADED":1545311033655,".DATE_CREATED":1545311013121,".BIRTH_SESSION":"qnpcbg09unjvdrez9ptxskm359wff0iweyzg4pfo3o975ew4ugscq45l4sqajzwn",".OID":"pv89rzfxeq8gowt5",".MODIFIED_BY":"4ilda7s9tsccna6t",".ORIGINAL_FILE_SIZE":"3867206",".FILE_SIZE":3869404,".LAST_SESSION":"w6rf7fuiskrxgeqy021ezbqevr6fx36jznpxt96cknzrsgfi87nx932uly08swii",".DATE_MODIFIED":1546020336305,".CLASS":"Image",".VERSION":3,"DPI":"200","Sensor":"Zeuchel A1 OS14000"}