{".FVER":1,".FILE_VERSION":1,"Archive ID":"701563",".CREATOR":"4ilda7s9tsccna6t",".MIME":"image/png",".IMAGE_HEIGHT":"1187",".NAME":"MOM_EST_701563_IE00129_V00_0001.png",".FILE_NAME":"MOM_EST_701563_IE00129_V00_0001.png","Handle of the 3D":"IE00129",".IMAGE_WIDTH":"2357",".FILE_ENCODING":"ds1_1","Squeeze Identifier":"UMR 5189 HiSoMA",".FILE_MODIFIED":1545081556000,".FILE_UPLOADED":1545274506900,".DATE_CREATED":1545274492067,".BIRTH_SESSION":"webqij2a09knux4rfj9ur04inyc7n979d9qmiim9iwm2khkpqj9894gnsjk5ii5m",".OID":"hnka5hwxve8jvcg8",".MODIFIED_BY":"4ilda7s9tsccna6t",".ORIGINAL_FILE_SIZE":"1950159",".FILE_SIZE":1951114,".LAST_SESSION":"w6rf7fuiskrxgeqy021ezbqevr6fx36jznpxt96cknzrsgfi87nx932uly08swii",".DATE_MODIFIED":1546020337448,".CLASS":"Image",".VERSION":3,"DPI":"200","Sensor":"Zeuchel A1 OS14000"}