{".FVER":1,".DATE_CREATED":1545330243864,".BIRTH_SESSION":"kobdm2rre0bach8cq55iram5lqmhuzq5er8qkq8og9piholxjh61hixsz90kzgf3",".LIST":{"yuw35f3lgxk2eghf":{".NAME":"MOM_EST_701742_IE00307_H00_0001.png",".CLASS":"Image"},"9mi4moxakvnnfzry":{".NAME":"MOM_EST_701742_IE00307",".CLASS":""},"zwkrna5pdbhhoyxd":{".NAME":"MOM_EST_701742_IE00307_V00_0001.png",".CLASS":"Image"}},".MODIFIED_BY":"8uqi0rivp58tr183",".OID":"9bbwz8sopymix0bi",".CREATOR":"8uqi0rivp58tr183",".LAST_SESSION":"9etsj6hgboqw0cofzv1wj3ooh69rz6rzbahk6pr748uua800usm3l0itxhbnescg",".NAME":"MOM_EST_701742_IE00307",".CLASS":"List",".DATE_MODIFIED":1546037044697,".VERSION":5}