{".FVER":1,".DATE_CREATED":1503959340395,".FILE_VERSION":4,".BIRTH_SESSION":"66etr76vln5knyayobpoz2fm23o7csw9p0s7yos92ojgcj4rlk5bcbn45128ko70",".OID":"qm4paz6llnft17ze",".MODIFIED_BY":"8uqi0rivp58tr183",".ORIGINAL_FILE_SIZE":"629714",".CREATOR":"8uqi0rivp58tr183",".FILE_SIZE":155999,".LAST_SESSION":"66etr76vln5knyayobpoz2fm23o7csw9p0s7yos92ojgcj4rlk5bcbn45128ko70",".NAME":"processing",".CLASS":"App",".DATE_MODIFIED":1504004799276,".FILE_ENCODING":"ds1_1",".VERSION":5,".FILE_MIME":"text/javascript; charset=utf-8",".FILE_UPLOADED":1504004799276}