{".FVER":1,".DATE_CREATED":1633115342736,".BIRTH_SESSION":"18ra457iq1i6u0g62f15zg9piz4prk4538i8rji0b9xqqmu2bf1v4l30pjo537d7",".CLASS":"App",".OID":"auue4sd80ekh7gtu",".VERSION":0,".CREATOR":"8uqi0rivp58tr183"},{".NAME":"CloudObjectCard",".T":54},{".T":75409,".LIST":{"s9g7h8913rfvm0wg":{".NAME":"NotificationCard",".CLASS":"App"}}},{".T":14282,".LIST":{"ivbwdjtw77uxpc7c":{".NAME":"HorizontalLayout",".CLASS":"App"}}},{".T":26661,".LIST":{"i48goijaln6rvsub":{".NAME":"Label",".CLASS":"App"}}},{"Assets":"{\"NotificationCard\":{\"id\":\"s9g7h8913rfvm0wg\",\"type\":\"App\"},\"HorizontalLayout\":{\"id\":\"ivbwdjtw77uxpc7c\",\"type\":\"App\"},\"Label\":{\"id\":\"i48goijaln6rvsub\",\"type\":\"App\"}}",".T":118936},{".FILE_VERSION":1,".T":134,".FILE_ENCODING":"ds1_1",".MIME":"text/javascript; charset=utf-8"},{".T":598366,".LIST":{"nkxbc2iqi2m976p9":{".NAME":"Image",".CLASS":"App"}}},{"Assets":"{\"HorizontalLayout\":{\"id\":\"ivbwdjtw77uxpc7c\",\"type\":\"App\"},\"Label\":{\"id\":\"i48goijaln6rvsub\",\"type\":\"App\"},\"NotificationCard\":{\"id\":\"s9g7h8913rfvm0wg\",\"type\":\"App\"},\"Image\":{\"id\":\"nkxbc2iqi2m976p9\",\"type\":\"App\"}}",".T":142874},{".FILE_VERSION":2,".T":126,".FILE_ENCODING":"ds1_1",".MIME":"text/javascript; charset=utf-8"},{".FILE_VERSION":3,".T":31160,".FILE_ENCODING":"ds1_1",".MIME":"text/javascript; charset=utf-8"}