{".FVER":1,".DATE_CREATED":1546024150966,".BIRTH_SESSION":"66p8r5ezvv80ri219hwxuu4fxtknwnjsjyr1uvqggp7yx0qx7ckswfyky8xll73v",".LIST":{"rlsj303exl3s2u6g":{".NAME":"MOM_EST_701623_IE00189_V00_0001.png",".CLASS":"Image"},"aayr9eg8ed3v8ase":{".NAME":"MOM_EST_701623_IE00189_H00_0001.png",".CLASS":"Image"}},".OID":"egmabjf08xzezhu8",".MODIFIED_BY":"8uqi0rivp58tr183","type":"heightmap","Archive ID":"701623",".CREATOR":"8uqi0rivp58tr183",".LAST_SESSION":"lh1rezke2nuc8ekticif3hqhuk4o59yggpylf8q7mbalfk4nmdtgkan5kikgh8mo",".NAME":"MOM_EST_701623_IE00189","Handle of the 3D":"IE00189",".OPEN":"j19tbvwezn6ugc8y",".DATE_MODIFIED":1547094898761,".VERSION":6,"DPI":"200","Squeeze Identifier":"UMR 5189 HiSoMA","Sensor":"Zeuchel A1 OS14000"}