{".FVER":1,".DATE_CREATED":1545311594908,".BIRTH_SESSION":"qnpcbg09unjvdrez9ptxskm359wff0iweyzg4pfo3o975ew4ugscq45l4sqajzwn",".LIST":{"6y2195kowa98zw1h":{".NAME":"MOM_EST_701602_IE00168_H00_0001.png",".CLASS":"Image"},"e4lkno1hkdc2tcbj":{".NAME":"MOM_EST_701602_IE00168_V00_0001.png",".CLASS":"Image"},"4z5byyhu76xllf6j":{".NAME":"MOM_EST_701602_IE00168",".CLASS":""}},".MODIFIED_BY":"8uqi0rivp58tr183",".OID":"7gxnikqrzji5apyw",".CREATOR":"8uqi0rivp58tr183",".LAST_SESSION":"9etsj6hgboqw0cofzv1wj3ooh69rz6rzbahk6pr748uua800usm3l0itxhbnescg",".NAME":"MOM_EST_701602_IE00168",".CLASS":"List",".DATE_MODIFIED":1546037042836,".VERSION":5}