{".FVER":1,".DATE_CREATED":1546024150941,".BIRTH_SESSION":"66p8r5ezvv80ri219hwxuu4fxtknwnjsjyr1uvqggp7yx0qx7ckswfyky8xll73v",".LIST":{"nkjwcu4wbzkcrxdj":{".NAME":"MOM_EST_701628_IE00193_H00_0001.png",".CLASS":"Image"},"9neggmxdoxy5wyx3":{".NAME":"MOM_EST_701628_IE00193_V00_0001.png",".CLASS":"Image"}},".OID":"q9lrkx065k2q9eqy",".MODIFIED_BY":"8uqi0rivp58tr183","type":"heightmap","Archive ID":"701628",".CREATOR":"8uqi0rivp58tr183",".LAST_SESSION":"lh1rezke2nuc8ekticif3hqhuk4o59yggpylf8q7mbalfk4nmdtgkan5kikgh8mo",".NAME":"MOM_EST_701628_IE00193","Handle of the 3D":"IE00193",".OPEN":"j19tbvwezn6ugc8y",".DATE_MODIFIED":1547094898717,".VERSION":6,"DPI":"200","Squeeze Identifier":"UMR 5189 HiSoMA","Sensor":"Zeuchel A1 OS14000"}