{".FVER":1,".DATE_CREATED":1511309871665,".FILE_VERSION":1,".BIRTH_SESSION":"5uzqdnx7jbm8cvir3vcynci308bqu7iqr86umusww5uzr2gkoj81lhvcfwt0t1gb",".OID":"wltrmr6zlx78dwns",".MODIFIED_BY":"czmjd0gan6mngf5u",".ORIGINAL_FILE_SIZE":"5898",".CREATOR":"czmjd0gan6mngf5u",".FILE_SIZE":5031,".MIME":"image/png",".LAST_SESSION":"5uzqdnx7jbm8cvir3vcynci308bqu7iqr86umusww5uzr2gkoj81lhvcfwt0t1gb",".IMAGE_HEIGHT":436,".NAME":"previous_button.png",".FILE_NAME":"previous_button.png",".IMAGE_WIDTH":436,".DATE_MODIFIED":1511309871800,".CLASS":"Image",".FILE_ENCODING":"ds1_1",".VERSION":2,".FILE_MODIFIED":1511310000341,".FILE_UPLOADED":1511309872009}