{".FVER":1,".DATE_CREATED":1546024152870,".BIRTH_SESSION":"66p8r5ezvv80ri219hwxuu4fxtknwnjsjyr1uvqggp7yx0qx7ckswfyky8xll73v",".LIST":{"jg8pc0be69evcr44":{".NAME":"MOM_EST_701879_400052_V00_0001.png",".CLASS":"Image"},"ef9xy4lxka6jh0sr":{".NAME":"MOM_EST_701879_400052_H00_0001.png",".CLASS":"Image"}},".OID":"bnweu26t6tjywgaa",".MODIFIED_BY":"8uqi0rivp58tr183","type":"heightmap","Archive ID":"701879",".CREATOR":"8uqi0rivp58tr183",".LAST_SESSION":"lh1rezke2nuc8ekticif3hqhuk4o59yggpylf8q7mbalfk4nmdtgkan5kikgh8mo",".NAME":"MOM_EST_701879_400052","Handle of the 3D":"400052",".OPEN":"j19tbvwezn6ugc8y",".DATE_MODIFIED":1547094900454,".VERSION":6,"DPI":"200","Squeeze Identifier":"UMR 5189 HiSoMA","Sensor":"Zeuchel A1 OS14000"}