{".FVER":1,".DATE_CREATED":1546024153162,".BIRTH_SESSION":"66p8r5ezvv80ri219hwxuu4fxtknwnjsjyr1uvqggp7yx0qx7ckswfyky8xll73v",".LIST":{"blw69n6qc9ibyz4l":{".NAME":"MOM_EST_701910_IE00399_V00_0001.png",".CLASS":"Image"},"haz3n41uqhk28e7b":{".NAME":"MOM_EST_701910_IE00399_H00_0001.png",".CLASS":"Image"}},".OID":"es2y85ba54yxdenp",".MODIFIED_BY":"8uqi0rivp58tr183","type":"heightmap","Archive ID":"701910",".CREATOR":"8uqi0rivp58tr183",".LAST_SESSION":"lh1rezke2nuc8ekticif3hqhuk4o59yggpylf8q7mbalfk4nmdtgkan5kikgh8mo",".NAME":"MOM_EST_701910_IE00399","Handle of the 3D":"IE00399",".OPEN":"j19tbvwezn6ugc8y",".DATE_MODIFIED":1547094900752,".VERSION":6,"DPI":"200","Squeeze Identifier":"UMR 5189 HiSoMA","Sensor":"Zeuchel A1 OS14000"}